fastmysql/__init__.py
fastmysql/fastmysql.py
fastmysql/fastmysql_test.py
fastmysql/lazymysql.py
fastmysql-0.3.7.dist-info/METADATA
fastmysql-0.3.7.dist-info/WHEEL
fastmysql-0.3.7.dist-info/top_level.txt
fastmysql-0.3.7.dist-info/RECORD
