Metadata-Version: 2.4
Name: fastmysql
Version: 0.3.7
Summary: make it easy to use pymysql
Home-page: https://gitee.com/ZeroSeeker/fastmysql
Author: ZeroSeeker
Author-email: zeroseeker@foxmail.com
Classifier: Programming Language :: Python :: 3
Classifier: Operating System :: OS Independent
Requires-Dist: envx>=1.0.1
Requires-Dist: numpy>=1.19.5
Requires-Dist: pandas>=1.3.5
Requires-Dist: PyMySQL==1.0.2
Requires-Dist: python-dateutil>=2.8.2
Requires-Dist: pytz==2022.1
Requires-Dist: showlog>=0.0.6
Requires-Dist: six==1.16.0
Requires-Dist: tqdm>=4.61.2
Requires-Dist: DBUtils==3.0.3
Dynamic: author
Dynamic: author-email
Dynamic: classifier
Dynamic: description
Dynamic: description-content-type
Dynamic: home-page
Dynamic: requires-dist
Dynamic: summary
